{
  "recentFiles": [
    {
      "basename": "File",
      "path": "Pemrograman Dasar/File.md"
    },
    {
      "basename": "Materi",
      "path": "Pemrograman Dasar/Materi.md"
    },
    {
      "basename": "Pemrograman Dasar",
      "path": "Pemrograman Dasar/Pemrograman Dasar.md"
    },
    {
      "basename": "File",
      "path": "Bahasa Indonesia/File.md"
    },
    {
      "basename": "Bahasa Indonesia",
      "path": "Bahasa Indonesia/Bahasa Indonesia.md"
    },
    {
      "basename": "Materi",
      "path": "Bahasa Indonesia/Materi.md"
    },
    {
      "basename": "Modul Tambahan - Penulisan Daftar Pustaka",
      "path": "Bahasa Indonesia/Materi/Modul Tambahan - Penulisan Daftar Pustaka.md"
    },
    {
      "basename": "Pertemuan 0405",
      "path": "Pemrograman Dasar/File/Pertemuan 0405.pdf"
    },
    {
      "basename": "Pertemuan 0203",
      "path": "Pemrograman Dasar/File/Pertemuan 0203.pdf"
    },
    {
      "basename": "Pertemuan 01",
      "path": "Pemrograman Dasar/File/Pertemuan 01.pdf"
    },
    {
      "basename": "EYD",
      "path": "Bahasa Indonesia/File/EYD.pdf"
    },
    {
      "basename": "Modul Tambahan - Sejarah Perkembangan dan Kedudukan Bahasa Indonesia",
      "path": "Bahasa Indonesia/Materi/Modul Tambahan - Sejarah Perkembangan dan Kedudukan Bahasa Indonesia.md"
    },
    {
      "basename": "Modul Tambahan - Imbuhan (Afiks)",
      "path": "Bahasa Indonesia/Materi/Modul Tambahan - Imbuhan (Afiks).md"
    },
    {
      "basename": "Modul Tambahan - Ejaan dan Kaidah Penulisan (EYD _ PUEBI)",
      "path": "Bahasa Indonesia/Materi/Modul Tambahan - Ejaan dan Kaidah Penulisan (EYD _ PUEBI).md"
    },
    {
      "basename": "Modul Tambahan - Bahasa Baku - Pengertian, Ciri, dan Sikap terhadap Bahasa",
      "path": "Bahasa Indonesia/Materi/Modul Tambahan - Bahasa Baku - Pengertian, Ciri, dan Sikap terhadap Bahasa.md"
    },
    {
      "basename": "Modul 7 - Pengertian Kalimat dan Jenis-Jenis Kalimat",
      "path": "Bahasa Indonesia/Materi/Modul 7 - Pengertian Kalimat dan Jenis-Jenis Kalimat.md"
    },
    {
      "basename": "Modul 6 - Istilah Sains dan Teknologi dalam Bahasa Indonesia",
      "path": "Bahasa Indonesia/Materi/Modul 6 - Istilah Sains dan Teknologi dalam Bahasa Indonesia.md"
    },
    {
      "basename": "Modul 5 - Diksi (Pilihan Kata)",
      "path": "Bahasa Indonesia/Materi/Modul 5 - Diksi (Pilihan Kata).md"
    },
    {
      "basename": "Modul 4 - Tanda Baca dan Kata Serapan dalam Bahasa Indonesia",
      "path": "Bahasa Indonesia/Materi/Modul 4 - Tanda Baca dan Kata Serapan dalam Bahasa Indonesia.md"
    },
    {
      "basename": "Modul 3 - Perkembangan Ejaan serta Huruf Kapital, Miring, dan Tebal",
      "path": "Bahasa Indonesia/Materi/Modul 3 - Perkembangan Ejaan serta Huruf Kapital, Miring, dan Tebal.md"
    },
    {
      "basename": "Modul 2 - Ragam Bahasa dan Laras Bahasa Indonesia",
      "path": "Bahasa Indonesia/Materi/Modul 2 - Ragam Bahasa dan Laras Bahasa Indonesia.md"
    },
    {
      "basename": "Modul 1 - Sejarah Perkembangan, Fungsi, dan Kedudukan Bahasa Indonesia",
      "path": "Bahasa Indonesia/Materi/Modul 1 - Sejarah Perkembangan, Fungsi, dan Kedudukan Bahasa Indonesia.md"
    }
  ],
  "omittedPaths": [],
  "omittedTags": [],
  "updateOn": "file-open",
  "omitBookmarks": false
}